package/__init__.py
package/main.py
pypostgresutil-1.0.2.dist-info/LICENSE
pypostgresutil-1.0.2.dist-info/METADATA
pypostgresutil-1.0.2.dist-info/WHEEL
pypostgresutil-1.0.2.dist-info/top_level.txt
pypostgresutil-1.0.2.dist-info/RECORD
