Metadata-Version: 2.1
Name: pypostgresutil
Version: 1.0.2
Summary: Python library for simple PostgreSQL management
Home-page: https://github.com/An0nX/PostgreSQLController
Author: An0nX
Author-email: example@gmail.com
Keywords: Python Library PostgreSQL Management Pypi Tool Database Interaction Relational Databases Python Programming
Classifier: Programming Language :: Python :: 3.11
Classifier: License :: OSI Approved :: MIT License
Classifier: Operating System :: OS Independent
Requires-Python: >=3.7
License-File: LICENSE
Requires-Dist: psycopg2
Requires-Dist: loguru
